aws_terraform_registry/__init__.py
aws_terraform_registry/__main__.py
aws_terraform_registry/cli.py
aws_terraform_registry/config.py
aws_terraform_registry/common/__init__.py
aws_terraform_registry/common/logger.py
aws_terraform_registry/common/matrix.py
aws_terraform_registry/common/model.py
aws_terraform_registry/common/publish.py
aws_terraform_registry/common/release.py
aws_terraform_registry/common/token.py
aws_terraform_registry-1.2.2.dist-info/METADATA
aws_terraform_registry-1.2.2.dist-info/WHEEL
aws_terraform_registry-1.2.2.dist-info/entry_points.txt
aws_terraform_registry-1.2.2.dist-info/top_level.txt
aws_terraform_registry-1.2.2.dist-info/RECORD
