Metadata-Version: 2.2
Name: aws_terraform_registry
Version: 1.2.2
Summary: Python client tool for aws private terraform registry.
Author-email: Jerome Guibert <jguibert@gmail.com>
License: The MIT License (MIT)
Project-URL: homepage, https://pypi.org/project/aws_terraform_registry
Project-URL: documentation, https://geronimo-iia.github.io/terraform-aws-tf-registry-cli/
Project-URL: repository, https://github.com/geronimo-iia/terraform-aws-tf-registry-cli
Classifier: Development Status :: 5 - Production/Stable
Classifier: Intended Audience :: Developers
Classifier: License :: OSI Approved :: MIT License
Classifier: Natural Language :: English
Classifier: Programming Language :: Python
Classifier: Programming Language :: Python :: 3
Classifier: Programming Language :: Python :: 3.9
Classifier: Programming Language :: Python :: 3.10
Classifier: Programming Language :: Python :: 3.11
Classifier: Programming Language :: Python :: 3.12
Classifier: Topic :: Software Development :: Libraries :: Python Modules
Classifier: Typing :: Typed
Requires-Python: <4,>=3.9
Requires-Dist: boto3~=1.26
Requires-Dist: pyjwt~=2.7.0
Requires-Dist: pyyaml~=6.0
Requires-Dist: envclasses~=0.3.1
Requires-Dist: python-dotenv~=1.0.0
Requires-Dist: crayons~=0.4.0
